manubot/__init__.py
manubot/command.py
manubot/util.py
manubot/ai_revision/__init__.py
manubot/ai_revision/ai_revision_command.py
manubot/cite/__init__.py
manubot/cite/arxiv.py
manubot/cite/citations.py
manubot/cite/cite_command.py
manubot/cite/citekey.py
manubot/cite/citeproc.py
manubot/cite/csl_item.py
manubot/cite/doi.py
manubot/cite/handlers.py
manubot/cite/isbn.py
manubot/cite/plain-pandoc-filter.lua
manubot/cite/pubmed.py
manubot/cite/unpaywall.py
manubot/cite/url.py
manubot/cite/wikidata.py
manubot/cite/zotero.py
manubot/cite/curie/__init__.py
manubot/cite/curie/bioregistry.json
manubot/pandoc/__init__.py
manubot/pandoc/bibliography.py
manubot/pandoc/cite_filter.py
manubot/pandoc/util.py
manubot/process/__init__.py
manubot/process/bibliography.py
manubot/process/ci.py
manubot/process/header-includes-template.html
manubot/process/manuscript.py
manubot/process/metadata.py
manubot/process/process_command.py
manubot/process/requests_cache.py
manubot/process/util.py
manubot/webpage/__init__.py
manubot/webpage/redirect-template.html
manubot/webpage/webpage_command.py
manubot-0.6.1.dist-info/LICENSE.md
manubot-0.6.1.dist-info/METADATA
manubot-0.6.1.dist-info/WHEEL
manubot-0.6.1.dist-info/entry_points.txt
manubot-0.6.1.dist-info/top_level.txt
manubot-0.6.1.dist-info/RECORD
