Metadata-Version: 2.1
Name: manubot
Version: 0.6.1
Summary: "Python utilities for Manubot: Manuscripts, open and automated"
Home-page: https://github.com/manubot/manubot
Maintainer: Daniel Himmelstein, Anthony Gitter
Maintainer-email: contact@manubot.org
License: BSD 3-Clause License
Project-URL: Source, https://github.com/manubot/manubot
Project-URL: Documentation, https://manubot.github.io/manubot
Project-URL: Tracker, https://github.com/manubot/manubot/issues
Project-URL: Homepage, https://manubot.org
Project-URL: Publication, https://greenelab.github.io/meta-review/
Keywords: manuscript,markdown,pandoc,publishing,references,citations,csl
Classifier: Intended Audience :: Science/Research
Classifier: Topic :: Scientific/Engineering :: Bio-Informatics
Classifier: Topic :: Scientific/Engineering :: Information Analysis
Classifier: License :: OSI Approved :: BSD License
Classifier: Programming Language :: Python :: 3
Classifier: Programming Language :: Python :: 3 :: Only
Requires-Python: >=3.8
License-File: LICENSE.md
Requires-Dist: errorhandler
Requires-Dist: isbnlib
Requires-Dist: jinja2
Requires-Dist: jsonschema >=3.0.0
Requires-Dist: packaging
Requires-Dist: panflute !=2.0.3,!=2.0.4
Requires-Dist: pybase62
Requires-Dist: pyyaml >=5.1
Requires-Dist: pyrate-limiter <3,>=2.6
Requires-Dist: requests-cache
Requires-Dist: requests
Requires-Dist: tomli ; python_version < "3.11"
Provides-Extra: ai-rev
Requires-Dist: manubot-ai-editor >=0.5.0 ; extra == 'ai-rev'
Provides-Extra: dev
Requires-Dist: portray ; extra == 'dev'
Requires-Dist: pre-commit ; extra == 'dev'
Requires-Dist: pytest >=6.0.0 ; extra == 'dev'
Requires-Dist: yamllint ; extra == 'dev'
Provides-Extra: webpage
Requires-Dist: opentimestamps-client ; extra == 'webpage'
